sqlite3_plus/__init__.py
sqlite3_plus/sqlite3_plus.py
sqlite3_plus-1.0.0.dist-info/LICENSE
sqlite3_plus-1.0.0.dist-info/METADATA
sqlite3_plus-1.0.0.dist-info/WHEEL
sqlite3_plus-1.0.0.dist-info/top_level.txt
sqlite3_plus-1.0.0.dist-info/RECORD
