Metadata-Version: 2.1
Name: sqlite3-plus
Version: 1.0.0
Summary: UNKNOWN
Home-page: UNKNOWN
Author: doesdoing
Author-email: doesdong@hotmail.com.com
License: UNKNOWN
Platform: UNKNOWN
Classifier: Programming Language :: Python :: 3
Classifier: License :: OSI Approved :: MIT License
Classifier: Operating System :: OS Independent
